solverpack/__init__.py
solverpack/BrokerMessage/__init__.py
solverpack/BrokerMessage/brocker_message.py
solverpack/Database/__init__.py
solverpack/Database/clear_table.py
solverpack/Database/download_table.py
solverpack/Database/upload_table.py
solverpack/Parser/__init__.py
solverpack/Parser/input_new_data.py
solverpack/Parser/ks_str_to_date.py
solverpack/Parser/traslate_excel_to_csv.py
solverpack-0.0.1.dist-info/METADATA
solverpack-0.0.1.dist-info/WHEEL
solverpack-0.0.1.dist-info/top_level.txt
solverpack-0.0.1.dist-info/RECORD
